pythonvideoannotator_module_motioncounter/__init__.py
pythonvideoannotator_module_motioncounter/module.py
pythonvideoannotator_module_motioncounter/motion_counter.py
pythonvideoannotator_module_motioncounter/models/__init__.py
pythonvideoannotator_module_motioncounter/models/video/__init__.py
pythonvideoannotator_module_motioncounter/models/video/objects/__init__.py
pythonvideoannotator_module_motioncounter/models/video/objects/object2d/__init__.py
pythonvideoannotator_module_motioncounter/models/video/objects/object2d/datasets/__init__.py
pythonvideoannotator_module_motioncounter/models/video/objects/object2d/datasets/motion_dataset.py
pythonvideoannotator_module_motioncounter/models/video/objects/object2d/datasets/contours/__init__.py
pythonvideoannotator_module_motioncounter/models/video/objects/object2d/datasets/path/__init__.py
Python_video_annotator_module_motion_counter-0.5.26.dist-info/METADATA
Python_video_annotator_module_motion_counter-0.5.26.dist-info/WHEEL
Python_video_annotator_module_motion_counter-0.5.26.dist-info/top_level.txt
Python_video_annotator_module_motion_counter-0.5.26.dist-info/RECORD
