Metadata-Version: 2.1
Name: Python-video-annotator-module-motion-counter
Version: 0.5.26
Summary: UNKNOWN
Home-page: https://bitbucket.org/fchampalimaud/pythonvideoannotator-module-motioncounter
Author: ['Ricardo Ribeiro']
Author-email: ricardojvr@gmail.com
License: UNKNOWN
Platform: UNKNOWN
